LICENSE
README.md
setup.cfg
setup.py
carefree_workflow.egg-info/PKG-INFO
carefree_workflow.egg-info/SOURCES.txt
carefree_workflow.egg-info/dependency_links.txt
carefree_workflow.egg-info/entry_points.txt
carefree_workflow.egg-info/requires.txt
carefree_workflow.egg-info/top_level.txt
cflow/__init__.py
cflow/cli.py
cflow/core.py
cflow/server.py
cflow/utils.py
cflow/nodes/__init__.py
cflow/nodes/common.py
cflow/nodes/cv.py
tests/test_examples.py
tests/test_server.py