Metadata-Version: 2.1
Name: carefree-workflow
Version: 0.1.0
Summary: Build arbitray workflows with Python!
Author: carefree0910
Author-email: syameimaru.saki@gmail.com
Keywords: python workflow
License-File: LICENSE
